dallasparser/__init__.py
dallasparser/cli.py
dallasparser/parser.py
dallasparser/regex.py
dallasparser/utils.py
dallasparser-0.2.dist-info/LICENSE
dallasparser-0.2.dist-info/METADATA
dallasparser-0.2.dist-info/WHEEL
dallasparser-0.2.dist-info/entry_points.txt
dallasparser-0.2.dist-info/top_level.txt
dallasparser-0.2.dist-info/RECORD
