Metadata-Version: 2.1
Name: dallasparser
Version: 0.2
Summary: TX Dallas Criminal Case Parser
Home-page: https://github.com/jaycatsby/tx_dallas_court_parser
Author: Jay Choi
Author-email: nobeedee@gmail.com
License: MIT
Keywords: texas dallas criminal court parser
Platform: UNKNOWN
Classifier: Programming Language :: Python :: 3
Classifier: License :: OSI Approved :: MIT License
Classifier: Operating System :: OS Independent
Requires-Python: >=3.6
Requires-Dist: beautifulsoup4 (==4.8.2)
Requires-Dist: bs4 (==0.0.1)
Requires-Dist: et-xmlfile (==1.0.1)
Requires-Dist: jdcal (==1.4.1)
Requires-Dist: lxml (==4.4.2)
Requires-Dist: numpy (==1.18.1)
Requires-Dist: openpyxl (==3.0.3)
Requires-Dist: pandas (==0.25.3)
Requires-Dist: python-dateutil (==2.8.1)
Requires-Dist: pytz (==2019.3)
Requires-Dist: six (==1.14.0)
Requires-Dist: soupsieve (==1.9.5)
Requires-Dist: tqdm (==4.41.1)
